{
  "schemaVersion": 1,
  "id": "piku",
  "version": "${version}",
  "name": "piku",
  "description": "",
  "authors": [],
  "contact": {},
  "license": "All-Rights-Reserved",
  "icon": "assets/piku/icon.png",
  "environment": "*",
  "entrypoints": {
    "fabric-datagen": [
      "computer.obscure.piku.client.PikuDataGenerator"
    ],
    "client": [
      "computer.obscure.piku.client.PikuClient"
    ],
    "main": [
      "computer.obscure.piku.Piku"
    ]
  },
  "mixins": [
    "piku.mixins.json",
    {
      "config": "piku.client.mixins.json",
      "environment": "client"
    }
  ],
  "depends": {
    "fabricloader": ">=${loader_version}",
    "fabric-language-kotlin": ">=${kotlin_loader_version}",
    "fabric-api": "*",
    "minecraft": "${minecraft_version}"
  }
}
